chromapie/__init__.py
chromapie/chromatise.py
chromapie/exceptions.py
chromapie/visuals.py
chromapie-0.0.3b0.dist-info/LICENSE
chromapie-0.0.3b0.dist-info/METADATA
chromapie-0.0.3b0.dist-info/WHEEL
chromapie-0.0.3b0.dist-info/top_level.txt
chromapie-0.0.3b0.dist-info/RECORD
