Metadata-Version: 2.2
Name: chromapie
Version: 0.0.3b0
Summary: A simple ANSI code wrapper I made to learn python packaging.
Author-email: Naut van der Winden <nautvanderwinden@gmail.com>
License: MIT License
Project-URL: Homepage, https://github.com/weescottishpuffin/chromapie
Project-URL: Issues, https://github.com/weescottishpuffin/chromapie/issues
Classifier: Programming Language :: Python :: 3
Classifier: Operating System :: OS Independent
Requires-Python: >=3.8
License-File: LICENSE
